visualize_algos/__init__.py
visualize_algos/path_finding_algos.py
visualize_algos/ui_based_path_search.py
visualize_algos-0.0.4.dist-info/METADATA
visualize_algos-0.0.4.dist-info/WHEEL
visualize_algos-0.0.4.dist-info/top_level.txt
visualize_algos-0.0.4.dist-info/RECORD
