Metadata-Version: 2.1
Name: visualize-algos
Version: 0.0.4
Summary: Visualize path finding algorithms simultaneously for the same condition in UI.
Home-page: https://github.com/Dhvanik-Viradiya/Path-finding-algorithm-visuallization
Author: Dhvanik Viradiya
Author-email: viradiyadhvanik@gmail.com
Classifier: Programming Language :: Python :: 3
Classifier: Operating System :: OS Independent
Requires-Python: >=3.6
